kafkaesk/__init__.py
kafkaesk/app.py
kafkaesk/consumer.py
kafkaesk/exceptions.py
kafkaesk/ext/__init__.py
kafkaesk/ext/logging/__init__.py
kafkaesk/ext/logging/handler.py
kafkaesk/ext/logging/record.py
kafkaesk/kafka.py
kafkaesk/metrics.py
kafkaesk/publish.py
kafkaesk/py.typed
kafkaesk/utils.py
kafkaesk-0.8.6.dist-info/LICENSE
kafkaesk-0.8.6.dist-info/METADATA
kafkaesk-0.8.6.dist-info/WHEEL
kafkaesk-0.8.6.dist-info/entry_points.txt
kafkaesk-0.8.6.dist-info/RECORD
