Metadata-Version: 2.1
Name: kafkaesk
Version: 0.8.6
Summary: Easy publish and subscribe to events with python and Kafka.
Author: vangheem
Author-email: vangheem@gmail.com
Requires-Python: >=3.10.1
Classifier: Framework :: AsyncIO
Classifier: License :: OSI Approved :: BSD License
Classifier: Programming Language :: Python :: 3
Classifier: Programming Language :: Python :: 3.11
Classifier: Programming Language :: Python :: 3.12
Classifier: Programming Language :: Python :: 3.13
Classifier: Programming Language :: Python :: 3.10
Classifier: Topic :: System :: Distributed Computing
Requires-Dist: aiokafka (>=0.7.1)
Requires-Dist: async-timeout (>=3.0.1)
Requires-Dist: jsonschema (>=3.2.0)
Requires-Dist: kafka-python (>=2.0.2,<3.0.0)
Requires-Dist: opentracing (>=2.3.0)
Requires-Dist: orjson (>=3.3.1)
Requires-Dist: prometheus_client (>=0.8.0)
Requires-Dist: pydantic (>=1.5.1)
Project-URL: GitHub, https://github.com/onna/kafkaesk
